[
    {
        "token": "CAG",
        "weight": 4.105988502502441
    },
    {
        "token": "GAT",
        "weight": 3.864408016204834
    },
    {
        "token": "GTC",
        "weight": 3.8435072898864746
    },
    {
        "token": "GCC",
        "weight": 3.6606009006500244
    },
    {
        "token": "GG",
        "weight": 3.5958738327026367
    },
    {
        "token": "GGT",
        "weight": 3.5817675590515137
    },
    {
        "token": "ATCC",
        "weight": 3.557206630706787
    },
    {
        "token": "ATT",
        "weight": 3.5281872749328613
    },
    {
        "token": "GAG",
        "weight": 3.5163724422454834
    },
    {
        "token": "GTT",
        "weight": 3.4748830795288086
    }
]